sqlalchemy_snowpark/__init__.py
sqlalchemy_snowpark/connection.py
sqlalchemy_snowpark/constants.py
sqlalchemy_snowpark/db_constants.py
sqlalchemy_snowpark/helper.py
sqlalchemy_snowpark/logger.py
sqlalchemy_snowpark/datawarehouse_connector/__init__.py
sqlalchemy_snowpark/datawarehouse_connector/postgresql_session.py
sqlalchemy_snowpark/datawarehouse_connector/redshift_session.py
sqlalchemy_snowpark/datawarehouse_connector/snowflake_session.py
sqlalchemy_snowpark/orm_manager/__init__.py
sqlalchemy_snowpark/orm_manager/base_session.py
sqlalchemy_snowpark/orm_manager/snowpark_session.py
sqlalchemy_snowpark/orm_manager/sqlalchemy_session.py
sqlalchemy_snowpark-1.4.dist-info/LICENSE
sqlalchemy_snowpark-1.4.dist-info/METADATA
sqlalchemy_snowpark-1.4.dist-info/WHEEL
sqlalchemy_snowpark-1.4.dist-info/top_level.txt
sqlalchemy_snowpark-1.4.dist-info/RECORD
