Metadata-Version: 2.1
Name: sqlalchemy-snowpark
Version: 1.4
Summary: A package for database session management using sqlalchemy and snowpark libraries
Home-page: https://ChandaniStepFunction@bitbucket.org/ChandaniStepFunction/sqlalchemy-snowpark.git
Author: Chandani Kumari
Author-email: chandani@stepfunction.ai
License: UNKNOWN
Platform: UNKNOWN
Classifier: Programming Language :: Python :: 3
Classifier: License :: OSI Approved :: MIT License
Classifier: Operating System :: OS Independent
Requires-Python: >=3.8
Requires-Dist: psycopg2-binary
Requires-Dist: redshift-connector
Requires-Dist: snowflake-connector-python
Requires-Dist: snowflake-sqlalchemy
Requires-Dist: SQLAlchemy
Requires-Dist: sqlalchemy-redshift
Requires-Dist: urllib3
Requires-Dist: snowflake-snowpark-python
Requires-Dist: sqlparse
